budg/__init__.py
budg/__main__.py
budg/config.py
budg/dataclassfromdict.py
budg/decoders.py
budg/exit.py
budg/importer.py
budg/main.py
budg/plugins/__init__.py
budg/plugins/copier.py
budg-1.0.0.dist-info/LICENSE
budg-1.0.0.dist-info/METADATA
budg-1.0.0.dist-info/WHEEL
budg-1.0.0.dist-info/entry_points.txt
budg-1.0.0.dist-info/top_level.txt
budg-1.0.0.dist-info/RECORD
