Metadata-Version: 2.1
Name: budg
Version: 1.0.0
Summary: A KISS Plugin Based Static Site Generator
Author-email: Fares Ahmed <fares@duck.com>
License: BSD Zero Clause License
Project-URL: Homepage, https://faresbakhit.github.io/budg
Requires-Python: >=3.8
License-File: LICENSE
Requires-Dist: dacite ~=1.8
Provides-Extra: dev
Requires-Dist: black ~=23.7 ; extra == 'dev'
Requires-Dist: isort ~=5.12 ; extra == 'dev'
Requires-Dist: mypy ~=1.5 ; extra == 'dev'
